{
    "@context": [
        "https://doi.org/10.5063/schema/codemeta-2.0",
        "http://schema.org"
    ],
    "@type": "SoftwareSourceCode",
    "author": [
        {
            "@type": "Person",
            "affiliation": {
                "@type": "Organization",
                "legalName": "Netherlands eScience Center"
            },
            "familyName": "Spaaks",
            "givenName": "Jurriaan H."
        },
        {
            "@type": "Person",
            "affiliation": {
                "@type": "Organization",
                "legalName": "Netherlands eScience Center"
            },
            "familyName": "Maassen",
            "givenName": "Jason"
        },
        {
            "@type": "Person",
            "affiliation": {
                "@type": "Organization",
                "legalName": "Netherlands eScience Center"
            },
            "familyName": "Klaver",
            "givenName": "Tom"
        },
        {
            "@type": "Person",
            "affiliation": {
                "@type": "Organization",
                "legalName": "Netherlands eScience Center"
            },
            "familyName": "Verhoeven",
            "givenName": "Stefan"
        },
        {
            "@type": "Person",
            "affiliation": {
                "@type": "Organization",
                "legalName": "Netherlands eScience Center"
            },
            "familyName": "van Hage",
            "givenName": "Willem"
        },
        {
            "@type": "Person",
            "affiliation": {
                "@type": "Organization",
                "legalName": "Netherlands eScience Center"
            },
            "familyName": "Ridder",
            "givenName": "Lars"
        },
        {
            "@type": "Person",
            "affiliation": {
                "@type": "Organization",
                "legalName": "Netherlands eScience Center"
            },
            "familyName": "Kulik",
            "givenName": "Lode"
        },
        {
            "@type": "Person",
            "affiliation": {
                "@type": "Organization",
                "legalName": "Netherlands eScience Center"
            },
            "familyName": "Bakker",
            "givenName": "Tom"
        },
        {
            "@type": "Person",
            "affiliation": {
                "@type": "Organization",
                "legalName": "Netherlands eScience Center"
            },
            "familyName": "van Hees",
            "givenName": "Vincent"
        },
        {
            "@type": "Person",
            "affiliation": {
                "@type": "Organization",
                "legalName": "Netherlands eScience Center"
            },
            "familyName": "Bogaardt",
            "givenName": "Laurens"
        },
        {
            "@type": "Person",
            "affiliation": {
                "@type": "Organization",
                "legalName": "Netherlands eScience Center"
            },
            "familyName": "Mendrik",
            "givenName": "Adriënne"
        },
        {
            "@type": "Person",
            "affiliation": {
                "@type": "Organization",
                "legalName": "Netherlands eScience Center"
            },
            "familyName": "van Es",
            "givenName": "Bram"
        },
        {
            "@type": "Person",
            "affiliation": {
                "@type": "Organization",
                "legalName": "Netherlands eScience Center"
            },
            "familyName": "Attema",
            "givenName": "Jisk"
        },
        {
            "@type": "Person",
            "affiliation": {
                "@type": "Organization",
                "legalName": "Netherlands eScience Center"
            },
            "familyName": "Ranguelova",
            "givenName": "Elena"
        },
        {
            "@type": "Person",
            "affiliation": {
                "@type": "Organization",
                "legalName": "Netherlands eScience Center"
            },
            "familyName": "van Nieuwpoort",
            "givenName": "Rob"
        }
    ],
    "codeRepository": "https://github.com/research-software-directory",
    "keywords": [
        "FAIR for software",
        "reproducible research",
        "research software",
        "RSE",
        "re-usable software"
    ],
    "license": "http://www.apache.org/licenses/LICENSE-2.0",
    "name": "Research Software Directory"
}
